tai_alphi/__init__.py
tai_alphi/config/__init__.py
tai_alphi/config/schemas.py
tai_alphi/exceptions/dependencies.py
tai_alphi/formatters/__init__.py
tai_alphi/formatters/console.py
tai_alphi/formatters/nosql.py
tai_alphi/formatters/teams.py
tai_alphi/handlers/__init__.py
tai_alphi/handlers/console.py
tai_alphi/handlers/nosql.py
tai_alphi/handlers/teams/__init__.py
tai_alphi/handlers/teams/cards.py
tai_alphi/logger.py
tai_alphi/resources/__init__.py
tai_alphi/resources/nosql.py
tai_alphi/resources/validations.py
tai_alphi-1.1.1.dist-info/LICENSE
tai_alphi-1.1.1.dist-info/METADATA
tai_alphi-1.1.1.dist-info/WHEEL
tai_alphi-1.1.1.dist-info/RECORD
