Metadata-Version: 2.3
Name: tai-alphi
Version: 1.1.1
Summary: Logs y monitorización de recursos
License: MIT
Keywords: logs,cloud
Author: MateoSaezMata
Author-email: msaez@triplealpha.in
Requires-Python: >=3.10,<4.0
Classifier: License :: OSI Approved :: MIT License
Classifier: Programming Language :: Python :: 3
Classifier: Programming Language :: Python :: 3.10
Classifier: Programming Language :: Python :: 3.11
Classifier: Programming Language :: Python :: 3.12
Classifier: Programming Language :: Python :: 3.13
Requires-Dist: pydantic (>=2.11,<3.0)
Requires-Dist: tomli (>=2.0.1,<3.0.0) ; python_version < "3.11"
Project-URL: Homepage, https://www.triplealpha.in/es/
Project-URL: Repository, https://github.com/triplealpha-innovation/tai-alphi
